[
  {
    "arguments": [
      "/usr/bin/g++",
      "-I../../../googletest/googletest/include/",
      "-I../../../shared/h",
      "-I../h",
      "-std=c++17",
      "-Wall",
      "-Wextra",
      "-Weffc++",
      "-Werror",
      "-g",
      "-coverage",
      "-D_GLIBCXX_USE_CXX11_ABI=0",
      "-c",
      "-o",
      "g++/guard_ut.o",
      "guard_ut.cpp"
    ],
    "directory": ".",
    "file": "./guard_ut.cpp",
    "output": "./g++/guard_ut.o"
  },
  {
    "arguments": [
      "/usr/bin/g++",
      "-I../../../googletest/googletest/include/",
      "-I../../../shared/h",
      "-I../h",
      "-std=c++17",
      "-Wall",
      "-Wextra",
      "-Weffc++",
      "-Werror",
      "-g",
      "-coverage",
      "-D_GLIBCXX_USE_CXX11_ABI=0",
      "-c",
      "-o",
      "g++/enum_operator_ut.o",
      "enum_operator_ut.cpp"
    ],
    "directory": ".",
    "file": "./enum_operator_ut.cpp",
    "output": "./g++/enum_operator_ut.o"
  },
  {
    "arguments": [
      "/usr/bin/g++",
      "-I../../../googletest/googletest/include/",
      "-I../../../shared/h",
      "-I../h",
      "-std=c++17",
      "-Wall",
      "-Wextra",
      "-Weffc++",
      "-Werror",
      "-g",
      "-coverage",
      "-D_GLIBCXX_USE_CXX11_ABI=0",
      "-c",
      "-o",
      "g++/copy_and_swap_ut.o",
      "copy_and_swap_ut.cpp"
    ],
    "directory": ".",
    "file": "./copy_and_swap_ut.cpp",
    "output": "./g++/copy_and_swap_ut.o"
  },
  {
    "arguments": [
      "/usr/bin/g++",
      "-I../../../googletest/googletest/include/",
      "-I../../../shared/h",
      "-I../h",
      "-std=c++17",
      "-Wall",
      "-Wextra",
      "-Weffc++",
      "-Werror",
      "-g",
      "-coverage",
      "-D_GLIBCXX_USE_CXX11_ABI=0",
      "-c",
      "-o",
      "g++/no_copy_and_swap_ut.o",
      "no_copy_and_swap_ut.cpp"
    ],
    "directory": ".",
    "file": "./no_copy_and_swap_ut.cpp",
    "output": "./g++/no_copy_and_swap_ut.o"
  },
  {
    "arguments": [
      "/usr/bin/g++",
      "-I../../../googletest/googletest/include/",
      "-I../../../shared/h",
      "-I../h",
      "-std=c++17",
      "-Wall",
      "-Wextra",
      "-Weffc++",
      "-Werror",
      "-g",
      "-coverage",
      "-D_GLIBCXX_USE_CXX11_ABI=0",
      "-c",
      "-o",
      "g++/string_holder_ut.o",
      "string_holder_ut.cpp"
    ],
    "directory": ".",
    "file": "./string_holder_ut.cpp",
    "output": "./g++/string_holder_ut.o"
  },
  {
    "arguments": [
      "/usr/bin/g++",
      "-I../../../googletest/googletest/include/",
      "-I../../../shared/h",
      "-I../h",
      "-std=c++17",
      "-Wall",
      "-Wextra",
      "-Weffc++",
      "-Werror",
      "-g",
      "-coverage",
      "-D_GLIBCXX_USE_CXX11_ABI=0",
      "-c",
      "-o",
      "g++/string_holder_new.o",
      "string_holder_new.cpp"
    ],
    "directory": ".",
    "file": "./string_holder_new.cpp",
    "output": "./g++/string_holder_new.o"
  },
  {
    "arguments": [
      "/usr/bin/g++",
      "-I../../../googletest/googletest/include/",
      "-I../../../shared/h",
      "-I../h",
      "-std=c++17",
      "-Wall",
      "-Wextra",
      "-Weffc++",
      "-Werror",
      "-g",
      "-coverage",
      "-D_GLIBCXX_USE_CXX11_ABI=0",
      "-c",
      "-o",
      "g++/string_holder_old.o",
      "string_holder_old.cpp"
    ],
    "directory": ".",
    "file": "./string_holder_old.cpp",
    "output": "./g++/string_holder_old.o"
  },
  {
    "arguments": [
      "/usr/bin/g++",
      "-I../../../googletest/googletest/include/",
      "-I../../../shared/h",
      "-I../h",
      "-std=c++17",
      "-Wall",
      "-Wextra",
      "-Weffc++",
      "-Werror",
      "-g",
      "-coverage",
      "-D_GLIBCXX_USE_CXX11_ABI=0",
      "-c",
      "-o",
      "g++/accessor_ut.o",
      "accessor_ut.cpp"
    ],
    "directory": ".",
    "file": "./accessor_ut.cpp",
    "output": "./g++/accessor_ut.o"
  },
  {
    "arguments": [
      "/usr/bin/g++",
      "-I../../../googletest/googletest/include/",
      "-I../../../shared/h",
      "-I../h",
      "-std=c++17",
      "-Wall",
      "-Wextra",
      "-Weffc++",
      "-Werror",
      "-g",
      "-coverage",
      "-D_GLIBCXX_USE_CXX11_ABI=0",
      "-c",
      "-o",
      "g++/clone_ut.o",
      "clone_ut.cpp"
    ],
    "directory": ".",
    "file": "./clone_ut.cpp",
    "output": "./g++/clone_ut.o"
  },
  {
    "arguments": [
      "/usr/bin/g++",
      "-I../../../googletest/googletest/include/",
      "-I../../../shared/h",
      "-I../h",
      "-std=c++17",
      "-Wall",
      "-Wextra",
      "-Weffc++",
      "-Werror",
      "-g",
      "-coverage",
      "-D_GLIBCXX_USE_CXX11_ABI=0",
      "-c",
      "-o",
      "g++/nvi_ut.o",
      "nvi_ut.cpp"
    ],
    "directory": ".",
    "file": "./nvi_ut.cpp",
    "output": "./g++/nvi_ut.o"
  },
  {
    "arguments": [
      "/usr/bin/g++",
      "-I../../../googletest/googletest/include/",
      "-I../../../shared/h",
      "-I../h",
      "-std=c++17",
      "-Wall",
      "-Wextra",
      "-Weffc++",
      "-Werror",
      "-g",
      "-coverage",
      "-D_GLIBCXX_USE_CXX11_ABI=0",
      "-c",
      "-o",
      "g++/raii_ut.o",
      "raii_ut.cpp"
    ],
    "directory": ".",
    "file": "./raii_ut.cpp",
    "output": "./g++/raii_ut.o"
  },
  {
    "arguments": [
      "/usr/bin/g++",
      "-I../../../googletest/googletest/include/",
      "-I../../../shared/h",
      "-I../h",
      "-std=c++17",
      "-Wall",
      "-Wextra",
      "-Weffc++",
      "-Werror",
      "-g",
      "-coverage",
      "-D_GLIBCXX_USE_CXX11_ABI=0",
      "-c",
      "-o",
      "g++/future_ut.o",
      "future_ut.cpp"
    ],
    "directory": ".",
    "file": "./future_ut.cpp",
    "output": "./g++/future_ut.o"
  },
  {
    "arguments": [
      "/usr/bin/g++",
      "-I../../../googletest/googletest/include/",
      "-I../../../shared/h",
      "-I../h",
      "-std=c++17",
      "-Wall",
      "-Wextra",
      "-Weffc++",
      "-Werror",
      "-g",
      "-coverage",
      "-D_GLIBCXX_USE_CXX11_ABI=0",
      "-c",
      "-o",
      "g++/di_ut.o",
      "di_ut.cpp"
    ],
    "directory": ".",
    "file": "./di_ut.cpp",
    "output": "./g++/di_ut.o"
  },
  {
    "arguments": [
      "/usr/bin/g++",
      "-I../../../googletest/googletest/include/",
      "-I../../../shared/h",
      "-I../h",
      "-std=c++17",
      "-Wall",
      "-Wextra",
      "-Weffc++",
      "-Werror",
      "-g",
      "-coverage",
      "-D_GLIBCXX_USE_CXX11_ABI=0",
      "-c",
      "-o",
      "g++/singleton_ut.o",
      "singleton_ut.cpp"
    ],
    "directory": ".",
    "file": "./singleton_ut.cpp",
    "output": "./g++/singleton_ut.o"
  },
  {
    "arguments": [
      "/usr/bin/g++",
      "-I../../../googletest/googletest/include/",
      "-I../../../shared/h",
      "-I../h",
      "-std=c++17",
      "-Wall",
      "-Wextra",
      "-Weffc++",
      "-Werror",
      "-g",
      "-coverage",
      "-D_GLIBCXX_USE_CXX11_ABI=0",
      "-c",
      "-o",
      "g++/state_machine_ut.o",
      "state_machine_ut.cpp"
    ],
    "directory": ".",
    "file": "./state_machine_ut.cpp",
    "output": "./g++/state_machine_ut.o"
  },
  {
    "arguments": [
      "/usr/bin/g++",
      "-I../../../googletest/googletest/include/",
      "-I../../../shared/h",
      "-I../h",
      "-std=c++17",
      "-Wall",
      "-Wextra",
      "-Weffc++",
      "-Werror",
      "-g",
      "-coverage",
      "-D_GLIBCXX_USE_CXX11_ABI=0",
      "-c",
      "-o",
      "g++/state_machine_new.o",
      "state_machine_new.cpp"
    ],
    "directory": ".",
    "file": "./state_machine_new.cpp",
    "output": "./g++/state_machine_new.o"
  },
  {
    "arguments": [
      "/usr/bin/g++",
      "-I../../../googletest/googletest/include/",
      "-I../../../shared/h",
      "-I../h",
      "-std=c++17",
      "-Wall",
      "-Wextra",
      "-Weffc++",
      "-Werror",
      "-g",
      "-coverage",
      "-D_GLIBCXX_USE_CXX11_ABI=0",
      "-c",
      "-o",
      "g++/state_machine_old.o",
      "state_machine_old.cpp"
    ],
    "directory": ".",
    "file": "./state_machine_old.cpp",
    "output": "./g++/state_machine_old.o"
  },
  {
    "arguments": [
      "/usr/bin/g++",
      "-I../../../googletest/googletest/include/",
      "-I../../../shared/h",
      "-I../h",
      "-std=c++17",
      "-Wall",
      "-Wextra",
      "-Weffc++",
      "-Werror",
      "-g",
      "-coverage",
      "-D_GLIBCXX_USE_CXX11_ABI=0",
      "-c",
      "-o",
      "g++/null_object_ut.o",
      "null_object_ut.cpp"
    ],
    "directory": ".",
    "file": "./null_object_ut.cpp",
    "output": "./g++/null_object_ut.o"
  },
  {
    "arguments": [
      "/usr/bin/g++",
      "-I../../../googletest/googletest/include/",
      "-I../../../shared/h",
      "-I../h",
      "-std=c++17",
      "-Wall",
      "-Wextra",
      "-Weffc++",
      "-Werror",
      "-g",
      "-coverage",
      "-D_GLIBCXX_USE_CXX11_ABI=0",
      "-c",
      "-o",
      "g++/template_method_factory_ut.o",
      "template_method_factory_ut.cpp"
    ],
    "directory": ".",
    "file": "./template_method_factory_ut.cpp",
    "output": "./g++/template_method_factory_ut.o"
  },
  {
    "arguments": [
      "/usr/bin/g++",
      "-I../../../googletest/googletest/include/",
      "-I../../../shared/h",
      "-I../h",
      "-std=c++17",
      "-Wall",
      "-Wextra",
      "-Weffc++",
      "-Werror",
      "-g",
      "-coverage",
      "-D_GLIBCXX_USE_CXX11_ABI=0",
      "-c",
      "-o",
      "g++/template_method_ut.o",
      "template_method_ut.cpp"
    ],
    "directory": ".",
    "file": "./template_method_ut.cpp",
    "output": "./g++/template_method_ut.o"
  },
  {
    "arguments": [
      "/usr/bin/g++",
      "-I../../../googletest/googletest/include/",
      "-I../../../shared/h",
      "-I../h",
      "-std=c++17",
      "-Wall",
      "-Wextra",
      "-Weffc++",
      "-Werror",
      "-g",
      "-coverage",
      "-D_GLIBCXX_USE_CXX11_ABI=0",
      "-c",
      "-o",
      "g++/template_method.o",
      "template_method.cpp"
    ],
    "directory": ".",
    "file": "./template_method.cpp",
    "output": "./g++/template_method.o"
  },
  {
    "arguments": [
      "/usr/bin/g++",
      "-I../../../googletest/googletest/include/",
      "-I../../../shared/h",
      "-I../h",
      "-std=c++17",
      "-Wall",
      "-Wextra",
      "-Weffc++",
      "-Werror",
      "-g",
      "-coverage",
      "-D_GLIBCXX_USE_CXX11_ABI=0",
      "-c",
      "-o",
      "g++/proxy_ut.o",
      "proxy_ut.cpp"
    ],
    "directory": ".",
    "file": "./proxy_ut.cpp",
    "output": "./g++/proxy_ut.o"
  },
  {
    "arguments": [
      "/usr/bin/g++",
      "-I../../../googletest/googletest/include/",
      "-I../../../shared/h",
      "-I../h",
      "-std=c++17",
      "-Wall",
      "-Wextra",
      "-Weffc++",
      "-Werror",
      "-g",
      "-coverage",
      "-D_GLIBCXX_USE_CXX11_ABI=0",
      "-c",
      "-o",
      "g++/bare_server.o",
      "bare_server.cpp"
    ],
    "directory": ".",
    "file": "./bare_server.cpp",
    "output": "./g++/bare_server.o"
  },
  {
    "arguments": [
      "/usr/bin/g++",
      "-I../../../googletest/googletest/include/",
      "-I../../../shared/h",
      "-I../h",
      "-std=c++17",
      "-Wall",
      "-Wextra",
      "-Weffc++",
      "-Werror",
      "-g",
      "-coverage",
      "-D_GLIBCXX_USE_CXX11_ABI=0",
      "-c",
      "-o",
      "g++/bare_server_wrapper.o",
      "bare_server_wrapper.cpp"
    ],
    "directory": ".",
    "file": "./bare_server_wrapper.cpp",
    "output": "./g++/bare_server_wrapper.o"
  },
  {
    "arguments": [
      "/usr/bin/g++",
      "-I../../../googletest/googletest/include/",
      "-I../../../shared/h",
      "-I../h",
      "-std=c++17",
      "-Wall",
      "-Wextra",
      "-Weffc++",
      "-Werror",
      "-g",
      "-coverage",
      "-D_GLIBCXX_USE_CXX11_ABI=0",
      "-c",
      "-o",
      "g++/wrapped_server.o",
      "wrapped_server.cpp"
    ],
    "directory": ".",
    "file": "./wrapped_server.cpp",
    "output": "./g++/wrapped_server.o"
  },
  {
    "arguments": [
      "/usr/bin/g++",
      "-I../../../googletest/googletest/include/",
      "-I../../../shared/h",
      "-I../h",
      "-std=c++17",
      "-Wall",
      "-Wextra",
      "-Weffc++",
      "-Werror",
      "-g",
      "-coverage",
      "-D_GLIBCXX_USE_CXX11_ABI=0",
      "-c",
      "-o",
      "g++/wrapped_server_proxy.o",
      "wrapped_server_proxy.cpp"
    ],
    "directory": ".",
    "file": "./wrapped_server_proxy.cpp",
    "output": "./g++/wrapped_server_proxy.o"
  },
  {
    "arguments": [
      "/usr/bin/g++",
      "-I../../../googletest/googletest/include/",
      "-I../../../shared/h",
      "-I../h",
      "-std=c++17",
      "-Wall",
      "-Wextra",
      "-Weffc++",
      "-Werror",
      "-g",
      "-coverage",
      "-D_GLIBCXX_USE_CXX11_ABI=0",
      "-c",
      "-o",
      "g++/class_ut.o",
      "class_ut.cpp"
    ],
    "directory": ".",
    "file": "./class_ut.cpp",
    "output": "./g++/class_ut.o"
  },
  {
    "arguments": [
      "/usr/bin/g++",
      "-I../../../googletest/googletest/include/",
      "-I../../../shared/h",
      "-I../h",
      "-std=c++17",
      "-Wall",
      "-Wextra",
      "-Weffc++",
      "-Werror",
      "-g",
      "-coverage",
      "-D_GLIBCXX_USE_CXX11_ABI=0",
      "-c",
      "-o",
      "g++/find_files_ut.o",
      "find_files_ut.cpp"
    ],
    "directory": ".",
    "file": "./find_files_ut.cpp",
    "output": "./g++/find_files_ut.o"
  },
  {
    "arguments": [
      "/usr/bin/g++",
      "-I../../../googletest/googletest/include/",
      "-I../../../shared/h",
      "-I../h",
      "-std=c++17",
      "-Wall",
      "-Wextra",
      "-Weffc++",
      "-Werror",
      "-g",
      "-coverage",
      "-D_GLIBCXX_USE_CXX11_ABI=0",
      "-c",
      "-o",
      "g++/find_files_strategy.o",
      "find_files_strategy.cpp"
    ],
    "directory": ".",
    "file": "./find_files_strategy.cpp",
    "output": "./g++/find_files_strategy.o"
  },
  {
    "arguments": [
      "/usr/bin/g++",
      "-I../../../googletest/googletest/include/",
      "-I../../../shared/h",
      "-I../h",
      "-std=c++17",
      "-Wall",
      "-Wextra",
      "-Weffc++",
      "-Werror",
      "-g",
      "-coverage",
      "-D_GLIBCXX_USE_CXX11_ABI=0",
      "-c",
      "-o",
      "g++/find_files_old_style.o",
      "find_files_old_style.cpp"
    ],
    "directory": ".",
    "file": "./find_files_old_style.cpp",
    "output": "./g++/find_files_old_style.o"
  },
  {
    "arguments": [
      "/usr/bin/g++",
      "-I../../../googletest/googletest/include/",
      "-I../../../shared/h",
      "-I../h",
      "-std=c++17",
      "-Wall",
      "-Wextra",
      "-Weffc++",
      "-Werror",
      "-g",
      "-coverage",
      "-D_GLIBCXX_USE_CXX11_ABI=0",
      "-c",
      "-o",
      "g++/visitor_ut.o",
      "visitor_ut.cpp"
    ],
    "directory": ".",
    "file": "./visitor_ut.cpp",
    "output": "./g++/visitor_ut.o"
  },
  {
    "arguments": [
      "/usr/bin/g++",
      "-I../../../googletest/googletest/include/",
      "-I../../../shared/h",
      "-I../h",
      "-std=c++17",
      "-Wall",
      "-Wextra",
      "-Weffc++",
      "-Werror",
      "-g",
      "-coverage",
      "-D_GLIBCXX_USE_CXX11_ABI=0",
      "-c",
      "-o",
      "g++/visitor.o",
      "visitor.cpp"
    ],
    "directory": ".",
    "file": "./visitor.cpp",
    "output": "./g++/visitor.o"
  },
  {
    "arguments": [
      "/usr/bin/g++",
      "-I../../../googletest/googletest/include/",
      "-I../../../shared/h",
      "-I../h",
      "-std=c++17",
      "-Wall",
      "-Wextra",
      "-Weffc++",
      "-Werror",
      "-g",
      "-coverage",
      "-D_GLIBCXX_USE_CXX11_ABI=0",
      "-c",
      "-o",
      "g++/crtp_ut.o",
      "crtp_ut.cpp"
    ],
    "directory": ".",
    "file": "./crtp_ut.cpp",
    "output": "./g++/crtp_ut.o"
  },
  {
    "arguments": [
      "/usr/bin/g++",
      "-I../../../googletest/googletest/include/",
      "-I../../../shared/h",
      "-I../h",
      "-std=c++17",
      "-Wall",
      "-Wextra",
      "-Weffc++",
      "-Werror",
      "-g",
      "-coverage",
      "-D_GLIBCXX_USE_CXX11_ABI=0",
      "-c",
      "-o",
      "g++/crtp.o",
      "crtp.cpp"
    ],
    "directory": ".",
    "file": "./crtp.cpp",
    "output": "./g++/crtp.o"
  },
  {
    "arguments": [
      "/usr/bin/g++",
      "-I../../../googletest/googletest/include/",
      "-I../../../shared/h",
      "-I../h",
      "-std=c++17",
      "-Wall",
      "-Wextra",
      "-Weffc++",
      "-Werror",
      "-g",
      "-coverage",
      "-D_GLIBCXX_USE_CXX11_ABI=0",
      "-c",
      "-o",
      "g++/observer_ut.o",
      "observer_ut.cpp"
    ],
    "directory": ".",
    "file": "./observer_ut.cpp",
    "output": "./g++/observer_ut.o"
  },
  {
    "arguments": [
      "/usr/bin/g++",
      "-I../../../googletest/googletest/include/",
      "-I../../../shared/h",
      "-I../h",
      "-std=c++17",
      "-Wall",
      "-Wextra",
      "-Weffc++",
      "-Werror",
      "-g",
      "-coverage",
      "-D_GLIBCXX_USE_CXX11_ABI=0",
      "-c",
      "-o",
      "g++/observer_ng.o",
      "observer_ng.cpp"
    ],
    "directory": ".",
    "file": "./observer_ng.cpp",
    "output": "./g++/observer_ng.o"
  },
  {
    "arguments": [
      "/usr/bin/g++",
      "-I../../../googletest/googletest/include/",
      "-I../../../shared/h",
      "-I../h",
      "-std=c++17",
      "-Wall",
      "-Wextra",
      "-Weffc++",
      "-Werror",
      "-g",
      "-coverage",
      "-D_GLIBCXX_USE_CXX11_ABI=0",
      "-c",
      "-o",
      "g++/observer_ok.o",
      "observer_ok.cpp"
    ],
    "directory": ".",
    "file": "./observer_ok.cpp",
    "output": "./g++/observer_ok.o"
  },
  {
    "arguments": [
      "/usr/bin/g++",
      "-I../../../googletest/googletest/include/",
      "-I../../../shared/h",
      "-I../h",
      "-std=c++17",
      "-Wall",
      "-Wextra",
      "-Weffc++",
      "-Werror",
      "-g",
      "-coverage",
      "-D_GLIBCXX_USE_CXX11_ABI=0",
      "-c",
      "-o",
      "g++/subject_ng.o",
      "subject_ng.cpp"
    ],
    "directory": ".",
    "file": "./subject_ng.cpp",
    "output": "./g++/subject_ng.o"
  },
  {
    "arguments": [
      "/usr/bin/g++",
      "-I../../../googletest/googletest/include/",
      "-I../../../shared/h",
      "-I../h",
      "-std=c++17",
      "-Wall",
      "-Wextra",
      "-Weffc++",
      "-Werror",
      "-g",
      "-coverage",
      "-D_GLIBCXX_USE_CXX11_ABI=0",
      "-c",
      "-o",
      "g++/subject_ok.o",
      "subject_ok.cpp"
    ],
    "directory": ".",
    "file": "./subject_ok.cpp",
    "output": "./g++/subject_ok.o"
  },
  {
    "arguments": [
      "/usr/bin/g++",
      "-I../../../googletest/googletest/include/",
      "-I",
      "../../../googletest/googletest/",
      "-D_GLIBCXX_USE_CXX11_ABI=0",
      "-c",
      "-o",
      "../gtest/g++/gtest-all.o",
      "../../../googletest/googletest/src/gtest-all.cc"
    ],
    "directory": ".",
    "file": "/home/ichiro/bitbucket/cpp_guideline/googletest/googletest/src/gtest-all.cc",
    "output": "/home/ichiro/bitbucket/cpp_guideline/shared/example/gtest/g++/gtest-all.o"
  },
  {
    "arguments": [
      "/usr/bin/g++",
      "-I../../../googletest/googletest/include/",
      "-I",
      "../../../googletest/googletest/",
      "-D_GLIBCXX_USE_CXX11_ABI=0",
      "-c",
      "-o",
      "../gtest/g++/gtest_main.o",
      "../../../googletest/googletest/src/gtest_main.cc"
    ],
    "directory": ".",
    "file": "/home/ichiro/bitbucket/cpp_guideline/googletest/googletest/src/gtest_main.cc",
    "output": "/home/ichiro/bitbucket/cpp_guideline/shared/example/gtest/g++/gtest_main.o"
  }
]
